gptcmd_anthropic/__init__.py
gptcmd_anthropic/anthropic.py
gptcmd_anthropic-1.2.1.dist-info/licenses/COPYING.txt
gptcmd_anthropic-1.2.1.dist-info/METADATA
gptcmd_anthropic-1.2.1.dist-info/WHEEL
gptcmd_anthropic-1.2.1.dist-info/entry_points.txt
gptcmd_anthropic-1.2.1.dist-info/top_level.txt
gptcmd_anthropic-1.2.1.dist-info/RECORD
