Metadata-Version: 2.4
Name: gptcmd-anthropic
Version: 1.2.1
Summary: Anthropic model support for Gptcmd
Author-email: Bill Dengler <codeofdusk@gmail.com>
Project-URL: Homepage, https://github.com/codeofdusk/gptcmd-anthropic
Project-URL: Bug Tracker, https://github.com/codeofdusk/gptcmd-anthropic/issues
Classifier: Programming Language :: Python :: 3
Classifier: License :: OSI Approved :: Mozilla Public License 2.0 (MPL 2.0)
Classifier: Operating System :: OS Independent
Requires-Python: >=3.8.6
License-File: COPYING.txt
Requires-Dist: gptcmd>=2.0.0
Requires-Dist: anthropic<1.0.0,>=0.42.0
Dynamic: license-file
